FuncToWav/__init__.py
FuncToWav/constants.py
FuncToWav/helper.py
FuncToWav/song_builder.py
FuncToWav/write_wav.py
FuncToWav-1.0.0.dist-info/LICENSE
FuncToWav-1.0.0.dist-info/METADATA
FuncToWav-1.0.0.dist-info/WHEEL
FuncToWav-1.0.0.dist-info/top_level.txt
FuncToWav-1.0.0.dist-info/RECORD
