Metadata-Version: 2.1
Name: FuncToWav
Version: 1.0.0
Summary: Given function, outputs wav file.
Home-page: https://github.com/pyj4104/FuncToWav
Author: YeounJun Park
Author-email: pyj4104@hotmail.com
License: UNKNOWN
Project-URL: Bug Tracker, https://github.com/pyj4104/FuncToWav/issues
Platform: UNKNOWN
Classifier: Programming Language :: Python :: 3
Classifier: License :: OSI Approved :: MIT License
Classifier: Operating System :: OS Independent
Requires-Python: >=3.8
